image_processing_malu/__init__.py
image_processing_malu/processing/__init__.py
image_processing_malu/processing/processing.py
image_processing_malu/utils/__init__.py
image_processing_malu/utils/utils.py
image_processing_malu-0.5.0.dist-info/METADATA
image_processing_malu-0.5.0.dist-info/WHEEL
image_processing_malu-0.5.0.dist-info/top_level.txt
image_processing_malu-0.5.0.dist-info/RECORD
