Metadata-Version: 2.4
Name: image_processing_malu
Version: 0.5.0
Summary: Pacote para processamento de imagens com histogram matching, similaridade estrutural e redimensionamento.
Home-page: https://github.com/malu-rm84/Package-dio
Author: Maria Luiza
Author-email: romani.malu84@gmail.com
Requires-Python: >=3.8
Requires-Dist: opencv-python>=4.7.0
Requires-Dist: numpy>=1.24.2
Requires-Dist: matplotlib==3.7.1
Requires-Dist: scikit-image>=0.20.0
Dynamic: author
Dynamic: author-email
Dynamic: description
Dynamic: description-content-type
Dynamic: home-page
Dynamic: requires-dist
Dynamic: requires-python
Dynamic: summary
